AsyncShipStation/__init__.py
AsyncShipStation/batches/__init__.py
AsyncShipStation/batches/_types.py
AsyncShipStation/batches/batches.py
AsyncShipStation/carriers/__init__.py
AsyncShipStation/carriers/_types.py
AsyncShipStation/carriers/carriers.py
AsyncShipStation/common/__init__.py
AsyncShipStation/common/_types.py
AsyncShipStation/common/base.py
AsyncShipStation/downloads/__init__.py
AsyncShipStation/downloads/downloads.py
AsyncShipStation/fulfillments/__init__.py
AsyncShipStation/fulfillments/_types.py
AsyncShipStation/fulfillments/fulfillments.py
AsyncShipStation/inventory/__init__.py
AsyncShipStation/inventory/_types.py
AsyncShipStation/inventory/inventory.py
AsyncShipStation/labels/__init__.py
AsyncShipStation/labels/_types.py
AsyncShipStation/labels/labels.py
AsyncShipStation/manifests/__init__.py
AsyncShipStation/manifests/_types.py
AsyncShipStation/manifests/manifests.py
AsyncShipStation/orders/__init__.py
AsyncShipStation/orders/_types.py
AsyncShipStation/orders/orders.py
AsyncShipStation/products/__init__.py
AsyncShipStation/products/_types.py
AsyncShipStation/products/products.py
AsyncShipStation/shipments/__init__.py
AsyncShipStation/shipments/_types.py
AsyncShipStation/shipments/shipments.py
asyncshipstation-0.1.0.7.dist-info/METADATA
asyncshipstation-0.1.0.7.dist-info/WHEEL
asyncshipstation-0.1.0.7.dist-info/RECORD
